Metadata-Version: 1.1
Name: ResNova
Version: 0.1.0
Summary: Cryogenic detectors for neutrino detection
Home-page: https://github.com/notacustomdev/ResNova
Author: Nahuel Ferreiro
Author-email: ferreiro@mpp.mpg.de
License: LICENSE.txt
Download-URL: https://github.com/notacustomdev/ResNova/archive/refs/tags/v_010.tar.gz
Platform: UNKNOWN
